control_unit.sv
module control_unit (input logic [3:0] opcode,
                     output logic [1:0] ALUControl,
                     output logic Branch, ALUSrc, RegWrite);

    always_comb begin

        case (opcode)
            4'b0000: begin RegWrite = 1 ;ALUSrc = 0 ;ALUControl = 2'b00 ;Branch = 0 ; end //and
            4'b0001: begin RegWrite = 1 ;ALUSrc = 0 ;ALUControl = 2'b01 ;Branch = 0 ; end//or
            4'b0010: begin RegWrite = 1 ;ALUSrc = 0 ;ALUControl = 2'b10 ;Branch = 0 ; end//add
            4'b0011: begin RegWrite = 1 ;ALUSrc = 0 ;ALUControl = 2'b11 ;Branch = 0 ; end//sub
            4'b0100: begin RegWrite = 1 ;ALUSrc = 1 ;ALUControl = 2'b00 ;Branch = 0 ; end//andi
            4'b0101: begin RegWrite = 1 ;ALUSrc = 1 ;ALUControl = 2'b01 ;Branch = 0 ; end//ori
            4'b0110: begin RegWrite = 1 ;ALUSrc = 1 ;ALUControl = 2'b10 ;Branch = 0 ; end//addi
            4'b0111: begin RegWrite = 0 ;ALUSrc = 0 ;ALUControl = 2'b11 ;Branch = 1 ; end//beq
            default: begin RegWrite = 1'bx ;ALUSrc = 1'bx ;ALUControl = 2'bxx ;Branch = 1'bx ;end
        endcase
        
    end

endmodule

control_unit_tb.sv
`timescale 1ps/1ps
`include "control_unit.sv"

module control_unit_tb;
logic [3:0] opcode;
logic [1:0] ALUControl;
logic Branch, ALUSrc, RegWrite;

control_unit dut (opcode,ALUControl,Branch,ALUSrc,RegWrite);

initial begin
    $dumpfile("control_unit_tb.vcd");
    $dumpvars(0,control_unit_tb);

    #10 opcode = 4'b0000; 
    #10 opcode = 4'b0001;
    #10 opcode = 4'b0010;
    #10 opcode = 4'b0011;
    #10 opcode = 4'b0100;
    #10 opcode = 4'b0101;
    #10 opcode = 4'b0110;
    #10 opcode = 4'b0111;

    $finish;

end

initial begin
    $monitor("time = %3d, opcode = %b,ALUControl =%b ,Branch = %b,ALUSrc = %b,RegWrite = %b",$time,opcode,ALUControl,Branch,ALUSrc,RegWrite);
end

endmodule

control_unit_tb.vcd
$date
	Fri Mar 03 23:13:56 2023
$end
$version
	Icarus Verilog
$end
$timescale
	1ps
$end
$scope module control_unit_tb $end
$var wire 1 ! RegWrite $end
$var wire 1 " Branch $end
$var wire 1 # ALUSrc $end
$var wire 2 $ ALUControl [1:0] $end
$var reg 4 % opcode [3:0] $end
$scope module dut $end
$var wire 4 & opcode [3:0] $end
$var reg 2 ' ALUControl [1:0] $end
$var reg 1 # ALUSrc $end
$var reg 1 " Branch $end
$var reg 1 ! RegWrite $end
$upscope $end
$upscope $end
$enddefinitions $end
$comment Show the parameter values. $end
$dumpall
$end
#0
$dumpvars
bx '
bx &
bx %
bx $
x#
x"
x!
$end
#10
0"
b0 $
b0 '
0#
1!
b0 %
b0 &
#20
b1 $
b1 '
b1 %
b1 &
#30
b10 $
b10 '
b10 %
b10 &
#40
b11 $
b11 '
b11 %
b11 &
#50
b0 $
b0 '
1#
b100 %
b100 &
#60
b1 $
b1 '
b101 %
b101 &
#70
b10 $
b10 '
b110 %
b110 &
#80
1"
b11 $
b11 '
0#
0!
b111 %
b111 &
