control_unit.sv
module control_unit (input logic [3:0] opcode,
                     output logic [1:0] ALUControl,
                     output logic Branch, ALUSrc, RegWrite);

    always_comb begin

        case (opcode)
            4'b0000: begin RegWrite = 1 ;ALUSrc = 0 ;ALUControl = 2'b00 ;Branch = 0 ; end //and
            4'b0001: begin RegWrite = 1 ;ALUSrc = 0 ;ALUControl = 2'b01 ;Branch = 0 ; end//or
            4'b0010: begin RegWrite = 1 ;ALUSrc = 0 ;ALUControl = 2'b10 ;Branch = 0 ; end//add
            4'b0011: begin RegWrite = 1 ;ALUSrc = 0 ;ALUControl = 2'b11 ;Branch = 0 ; end//sub
            4'b0100: begin RegWrite = 1 ;ALUSrc = 1 ;ALUControl = 2'b00 ;Branch = 0 ; end//andi
            4'b0101: begin RegWrite = 1 ;ALUSrc = 1 ;ALUControl = 2'b01 ;Branch = 0 ; end//ori
            4'b0110: begin RegWrite = 1 ;ALUSrc = 1 ;ALUControl = 2'b10 ;Branch = 0 ; end//addi
            4'b0111: begin RegWrite = 0 ;ALUSrc = 0 ;ALUControl = 2'b11 ;Branch = 1 ; end//beq
            default: begin RegWrite = 1'bx ;ALUSrc = 1'bx ;ALUControl = 2'bxx ;Branch = 1'bx ;end
        endcase
        
    end

endmodule

instruction_memory.sv
module instruction_memory (input logic [7:0] PC, 
                           output logic [23:0] Instr); 

logic [24:0] data_ROM [0:255]; 

initial begin
    $readmemh("program.txt", data_ROM);
end

assign Instr = data_ROM[PC]; 

endmodule

pc.sv
module pc (input logic [7:0] immediate,
           input logic PCSrc, CLK, reset,
           output logic [7:0] PC);

    logic [7:0] PC_temp;
    
    always_comb begin

        if (PCSrc) begin
            PC_temp = immediate;
        end

        else begin
            PC_temp = PC + 8'b01;
        end            
        
    end


    always_ff @( posedge CLK ) begin

        if (reset) begin    
            PC <= 0;
        end 
        else begin
            PC <= PC_temp;
        end
            
    end

    
endmodule

instruction_memory_pc.sv
`include "instruction_memory.sv"
`include "pc.sv"

module instruction_memory_pc (input logic [7:0] immediate,
                              input logic PCSrc, CLK, reset, 
                              output logic [23:0] Instr);

    logic [7:0] PC;

    pc pc_in (immediate,PCSrc, CLK, reset,PC);

    instruction_memory instruction_memory_in (PC,Instr);

    
endmodule

reg_file.sv
module reg_file (input logic [3:0] RA1,RA2,WA,
                 input logic [7:0] ALUResult,
                 input logic write_enable,CLK,
                 output logic [7:0] RD1,RD2,cpu_out);
    
    logic [7:0] rf [0:15];
    assign RD1 = rf[RA1];
    assign RD2 = rf[RA2];

    always_comb begin
        rf[0] = 8'b0;
    end
    
    always_ff @( posedge CLK ) begin
        if (write_enable && WA > 0) begin
            rf[WA] <= ALUResult;
        end

        cpu_out <= rf[15];
    end

endmodule

alu.sv
module alu (input logic [7:0] SrcA,SrcB,
            input logic [1:0] ALUControl,
            output logic [7:0] ALUResult,
            output logic Zero);
    always_comb begin

        case(ALUControl)
        2'b00: ALUResult = SrcA & SrcB;
        2'b01: ALUResult = SrcA | SrcB;
        2'b10: ALUResult = SrcA + SrcB;
        2'b11: ALUResult = SrcA - SrcB;
        default: ALUResult = 8'bx;
        endcase

        if(ALUResult == 0) begin
            Zero = 1;
        end
        else begin
            Zero = 0;
        end
    end

  
endmodule

reg_file_alu.sv
`include "alu.sv"
`include "reg_file.sv"

module reg_file_alu (input logic [3:0] RA1,RA2,WA,
                     input logic [7:0] immediate,
                     input logic [1:0] ALUControl,
                     input logic write_enable, ALUSrc, CLK,
                     output logic [7:0] ALUResult,cpu_out,
                     output logic Zero);

    logic [7:0] SrcA,SrcB,RD1,RD2;

    alu alu_in (SrcA,SrcB,ALUControl,ALUResult,Zero);

    reg_file reg_file_in (RA1,RA2,WA,ALUResult,write_enable,CLK,RD1,RD2,cpu_out);

    always_comb begin

        SrcA = RD1;

        if (ALUSrc) begin
            SrcB = immediate;
        end
        else begin
            SrcB = RD2; 
        end
    end

endmodule

cpu.sv
`include "reg_file_alu.sv"
`include "instruction_memory_pc.sv"
`include "control_unit.sv"

module cpu (input logic CLK, reset, 
            output logic [7:0] ALUResult, cpu_out);

    logic [3:0] RA1, RA2, WA, opcode;
    logic [7:0] immediate;
    logic [1:0] ALUControl;
    logic write_enable, ALUSrc, Zero, PCSrc, Branch, RegWrite;
    logic [23:0] Instr;

    assign immediate = Instr[7:0];
    assign RA2 = Instr[11:8];
    assign RA1 = Instr[15:12];
    assign WA = Instr[19:16];
    assign opcode = Instr[23:20];

    assign write_enable = RegWrite;

    assign PCSrc = Branch & Zero;

    reg_file_alu reg_file_alu_in (RA1,RA2,WA,immediate,ALUControl,write_enable, ALUSrc, CLK,ALUResult,cpu_out,Zero);
    instruction_memory_pc instruction_memory_pc_in (immediate,PCSrc, CLK, reset,Instr);
    control_unit control_unit_in (opcode,ALUControl,Branch, ALUSrc, RegWrite);


    
endmodule

cpu_tb.sv
`timescale 1ps/1ps
`include "cpu.sv"

module cpu_tb;
logic CLK, reset;
logic [7:0] ALUResult, cpu_out;

cpu dut (CLK,reset,ALUResult,cpu_out);

initial begin
    CLK = 0;
    forever begin
        #10 CLK = ~CLK;
    end
end

initial begin
    $dumpfile("cpu_tb.vcd");
    $dumpvars(0,cpu_tb);    

    reset = 1;
    #10
    #10 reset = 0;
    #510


    $finish;
end

initial begin
    $monitor("time = %3d, ALUResult = %d, cpu_out = %d", $time, ALUResult, cpu_out);
end


endmodule

cpu_tb.vcd
$date
	Fri Mar 03 23:08:20 2023
$end
$version
	Icarus Verilog
$end
$timescale
	1ps
$end
$scope module cpu_tb $end
$var wire 8 ! cpu_out [7:0] $end
$var wire 8 " ALUResult [7:0] $end
$var reg 1 # CLK $end
$var reg 1 $ reset $end
$scope module dut $end
$var wire 1 # CLK $end
$var wire 1 % PCSrc $end
$var wire 1 $ reset $end
$var wire 1 & write_enable $end
$var wire 4 ' opcode [3:0] $end
$var wire 8 ( immediate [7:0] $end
$var wire 8 ) cpu_out [7:0] $end
$var wire 1 * Zero $end
$var wire 4 + WA [3:0] $end
$var wire 1 , RegWrite $end
$var wire 4 - RA2 [3:0] $end
$var wire 4 . RA1 [3:0] $end
$var wire 24 / Instr [23:0] $end
$var wire 1 0 Branch $end
$var wire 1 1 ALUSrc $end
$var wire 8 2 ALUResult [7:0] $end
$var wire 2 3 ALUControl [1:0] $end
$scope module control_unit_in $end
$var wire 4 4 opcode [3:0] $end
$var reg 2 5 ALUControl [1:0] $end
$var reg 1 1 ALUSrc $end
$var reg 1 0 Branch $end
$var reg 1 , RegWrite $end
$upscope $end
$scope module instruction_memory_pc_in $end
$var wire 1 # CLK $end
$var wire 1 % PCSrc $end
$var wire 8 6 immediate [7:0] $end
$var wire 1 $ reset $end
$var wire 8 7 PC [7:0] $end
$var wire 24 8 Instr [23:0] $end
$scope module instruction_memory_in $end
$var wire 8 9 PC [7:0] $end
$var wire 24 : Instr [23:0] $end
$upscope $end
$scope module pc_in $end
$var wire 1 # CLK $end
$var wire 1 % PCSrc $end
$var wire 8 ; immediate [7:0] $end
$var wire 1 $ reset $end
$var reg 8 < PC [7:0] $end
$var reg 8 = PC_temp [7:0] $end
$upscope $end
$upscope $end
$scope module reg_file_alu_in $end
$var wire 2 > ALUControl [1:0] $end
$var wire 1 1 ALUSrc $end
$var wire 1 # CLK $end
$var wire 4 ? RA1 [3:0] $end
$var wire 4 @ RA2 [3:0] $end
$var wire 4 A WA [3:0] $end
$var wire 8 B immediate [7:0] $end
$var wire 1 & write_enable $end
$var wire 8 C cpu_out [7:0] $end
$var wire 1 * Zero $end
$var wire 8 D RD2 [7:0] $end
$var wire 8 E RD1 [7:0] $end
$var wire 8 F ALUResult [7:0] $end
$var reg 8 G SrcA [7:0] $end
$var reg 8 H SrcB [7:0] $end
$scope module alu_in $end
$var wire 2 I ALUControl [1:0] $end
$var wire 8 J SrcA [7:0] $end
$var wire 8 K SrcB [7:0] $end
$var reg 8 L ALUResult [7:0] $end
$var reg 1 * Zero $end
$upscope $end
$scope module reg_file_in $end
$var wire 8 M ALUResult [7:0] $end
$var wire 1 # CLK $end
$var wire 4 N RA1 [3:0] $end
$var wire 4 O RA2 [3:0] $end
$var wire 8 P RD1 [7:0] $end
$var wire 8 Q RD2 [7:0] $end
$var wire 4 R WA [3:0] $end
$var wire 1 & write_enable $end
$var reg 8 S cpu_out [7:0] $end
$upscope $end
$upscope $end
$upscope $end
$upscope $end
$enddefinitions $end
$comment Show the parameter values. $end
$dumpall
$end
#0
$dumpvars
bx S
bx R
bx Q
bx P
bx O
bx N
bx M
bx L
bx K
bx J
bx I
bx H
bx G
bx F
bx E
bx D
bx C
bx B
bx A
bx @
bx ?
bx >
bx =
bx <
bx ;
bx :
bx 9
bx 8
bx 7
bx 6
bx 5
bx 4
bx 3
bx 2
x1
x0
bx /
bx .
bx -
x,
bx +
0*
bx )
bx (
bx '
x&
0%
1$
0#
bx "
bx !
$end
#10
0*
b1 "
b1 2
b1 F
b1 L
b1 M
00
b10 3
b10 5
b10 >
b10 I
11
1&
1,
b1 H
b1 K
b0 G
b0 J
b110 '
b110 4
b1 +
b1 A
b1 R
b0 E
b0 P
b0 .
b0 ?
b0 N
b0 D
b0 Q
b0 -
b0 @
b0 O
b1 (
b1 6
b1 ;
b1 B
b11000010000000000000001 /
b11000010000000000000001 8
b11000010000000000000001 :
b1 =
b0 7
b0 9
b0 <
1#
#20
0$
0#
#30
b100000 "
b100000 2
b100000 F
b100000 L
b100000 M
b100000 H
b100000 K
b10 +
b10 A
b10 R
b100000 (
b100000 6
b100000 ;
b100000 B
b11000100000000000100000 /
b11000100000000000100000 8
b11000100000000000100000 :
b10 =
b1 7
b1 9
b1 <
1#
#40
0#
#50
1*
b0 "
b0 2
b0 F
b0 L
b0 M
b0 H
b0 K
b1111 +
b1111 A
b1111 R
b0 (
b0 6
b0 ;
b0 B
b11011110000000000000000 /
b11011110000000000000000 8
b11011110000000000000000 :
b11 =
b10 7
b10 9
b10 <
1#
#60
0#
#70
0*
b11100001 "
b11100001 2
b11100001 F
b11100001 L
b11100001 M
10
b11 3
b11 5
b11 >
b11 I
01
0&
0,
b100000 H
b100000 K
b1 G
b1 J
b111 '
b111 4
b0 +
b0 A
b0 R
b1 E
b1 P
b1 .
b1 ?
b1 N
b100000 D
b100000 Q
b10 -
b10 @
b10 O
b111 (
b111 6
b111 ;
b111 B
b11100000001001000000111 /
b11100000001001000000111 8
b11100000001001000000111 :
b100 =
b11 7
b11 9
b11 <
1#
#80
0#
#90
b10 "
b10 2
b10 F
b10 L
b10 M
00
b10 3
b10 5
b10 >
b10 I
1&
1,
b1 H
b1 K
b10 '
b10 4
b1 +
b1 A
b1 R
b1 D
b1 Q
b1 -
b1 @
b1 O
b0 (
b0 6
b0 ;
b0 B
b1000010001000100000000 /
b1000010001000100000000 8
b1000010001000100000000 :
b101 =
b0 !
b0 )
b0 C
b0 S
b100 7
b100 9
b100 <
1#
#100
0#
#110
0*
11
b110 '
b110 4
b1111 +
b1111 A
b1111 R
b1111 .
b1111 ?
b1111 N
b0 -
b0 @
b0 O
b1 (
b1 6
b1 ;
b1 B
b1 "
b1 2
b1 F
b1 L
b1 M
b11011111111000000000001 /
b11011111111000000000001 8
b11011111111000000000001 :
b110 =
b1 H
b1 K
b0 G
b0 J
b101 7
b101 9
b101 <
b0 E
b0 P
b0 D
b0 Q
1#
#120
0#
#130
1%
1*
10
b11 3
b11 5
b11 >
b11 I
01
0&
0,
b0 H
b0 K
b0 "
b0 2
b0 F
b0 L
b0 M
b111 '
b111 4
b0 +
b0 A
b0 R
b0 .
b0 ?
b0 N
b11 (
b11 6
b11 ;
b11 B
b0 G
b0 J
b11100000000000000000011 /
b11100000000000000000011 8
b11100000000000000000011 :
b11 =
b0 E
b0 P
b110 7
b110 9
b110 <
1#
#140
0#
#150
0%
0*
b11100010 "
b11100010 2
b11100010 F
b11100010 L
b11100010 M
b100 =
b100000 H
b100000 K
b10 G
b10 J
b10 E
b10 P
b1 .
b1 ?
b1 N
b100000 D
b100000 Q
b10 -
b10 @
b10 O
b111 (
b111 6
b111 ;
b111 B
b11100000001001000000111 /
b11100000001001000000111 8
b11100000001001000000111 :
b11 7
b11 9
b11 <
b1 !
b1 )
b1 C
b1 S
1#
#160
0#
#170
b100 "
b100 2
b100 F
b100 L
b100 M
00
b10 3
b10 5
b10 >
b10 I
1&
1,
b10 H
b10 K
b10 '
b10 4
b1 +
b1 A
b1 R
b10 D
b10 Q
b1 -
b1 @
b1 O
b0 (
b0 6
b0 ;
b0 B
b1000010001000100000000 /
b1000010001000100000000 8
b1000010001000100000000 :
b101 =
b100 7
b100 9
b100 <
1#
#180
0#
#190
11
b110 '
b110 4
b1111 +
b1111 A
b1111 R
b1111 .
b1111 ?
b1111 N
b0 -
b0 @
b0 O
b1 (
b1 6
b1 ;
b1 B
b10 "
b10 2
b10 F
b10 L
b10 M
b11011111111000000000001 /
b11011111111000000000001 8
b11011111111000000000001 :
b110 =
b1 H
b1 K
b1 G
b1 J
b101 7
b101 9
b101 <
b1 E
b1 P
b0 D
b0 Q
1#
#200
0#
#210
1%
1*
10
b11 3
b11 5
b11 >
b11 I
01
0&
0,
b0 H
b0 K
b0 "
b0 2
b0 F
b0 L
b0 M
b111 '
b111 4
b0 +
b0 A
b0 R
b0 .
b0 ?
b0 N
b11 (
b11 6
b11 ;
b11 B
b0 G
b0 J
b11100000000000000000011 /
b11100000000000000000011 8
b11100000000000000000011 :
b11 =
b0 E
b0 P
b110 7
b110 9
b110 <
1#
#220
0#
#230
0%
0*
b11100100 "
b11100100 2
b11100100 F
b11100100 L
b11100100 M
b100 =
b100000 H
b100000 K
b100 G
b100 J
b100 E
b100 P
b1 .
b1 ?
b1 N
b100000 D
b100000 Q
b10 -
b10 @
b10 O
b111 (
b111 6
b111 ;
b111 B
b11100000001001000000111 /
b11100000001001000000111 8
b11100000001001000000111 :
b11 7
b11 9
b11 <
b10 !
b10 )
b10 C
b10 S
1#
#240
0#
#250
b1000 "
b1000 2
b1000 F
b1000 L
b1000 M
00
b10 3
b10 5
b10 >
b10 I
1&
1,
b100 H
b100 K
b10 '
b10 4
b1 +
b1 A
b1 R
b100 D
b100 Q
b1 -
b1 @
b1 O
b0 (
b0 6
b0 ;
b0 B
b1000010001000100000000 /
b1000010001000100000000 8
b1000010001000100000000 :
b101 =
b100 7
b100 9
b100 <
1#
#260
0#
#270
11
b110 '
b110 4
b1111 +
b1111 A
b1111 R
b1111 .
b1111 ?
b1111 N
b0 -
b0 @
b0 O
b1 (
b1 6
b1 ;
b1 B
b11 "
b11 2
b11 F
b11 L
b11 M
b11011111111000000000001 /
b11011111111000000000001 8
b11011111111000000000001 :
b110 =
b1 H
b1 K
b10 G
b10 J
b101 7
b101 9
b101 <
b10 E
b10 P
b0 D
b0 Q
1#
#280
0#
#290
1%
1*
10
b11 3
b11 5
b11 >
b11 I
01
0&
0,
b0 H
b0 K
b0 "
b0 2
b0 F
b0 L
b0 M
b111 '
b111 4
b0 +
b0 A
b0 R
b0 .
b0 ?
b0 N
b11 (
b11 6
b11 ;
b11 B
b0 G
b0 J
b11100000000000000000011 /
b11100000000000000000011 8
b11100000000000000000011 :
b11 =
b0 E
b0 P
b110 7
b110 9
b110 <
1#
#300
0#
#310
0%
0*
b11101000 "
b11101000 2
b11101000 F
b11101000 L
b11101000 M
b100 =
b100000 H
b100000 K
b1000 G
b1000 J
b1000 E
b1000 P
b1 .
b1 ?
b1 N
b100000 D
b100000 Q
b10 -
b10 @
b10 O
b111 (
b111 6
b111 ;
b111 B
b11100000001001000000111 /
b11100000001001000000111 8
b11100000001001000000111 :
b11 7
b11 9
b11 <
b11 !
b11 )
b11 C
b11 S
1#
#320
0#
#330
b10000 "
b10000 2
b10000 F
b10000 L
b10000 M
00
b10 3
b10 5
b10 >
b10 I
1&
1,
b1000 H
b1000 K
b10 '
b10 4
b1 +
b1 A
b1 R
b1000 D
b1000 Q
b1 -
b1 @
b1 O
b0 (
b0 6
b0 ;
b0 B
b1000010001000100000000 /
b1000010001000100000000 8
b1000010001000100000000 :
b101 =
b100 7
b100 9
b100 <
1#
#340
0#
#350
11
b110 '
b110 4
b1111 +
b1111 A
b1111 R
b1111 .
b1111 ?
b1111 N
b0 -
b0 @
b0 O
b1 (
b1 6
b1 ;
b1 B
b100 "
b100 2
b100 F
b100 L
b100 M
b11011111111000000000001 /
b11011111111000000000001 8
b11011111111000000000001 :
b110 =
b1 H
b1 K
b11 G
b11 J
b101 7
b101 9
b101 <
b11 E
b11 P
b0 D
b0 Q
1#
#360
0#
#370
1%
1*
10
b11 3
b11 5
b11 >
b11 I
01
0&
0,
b0 H
b0 K
b0 "
b0 2
b0 F
b0 L
b0 M
b111 '
b111 4
b0 +
b0 A
b0 R
b0 .
b0 ?
b0 N
b11 (
b11 6
b11 ;
b11 B
b0 G
b0 J
b11100000000000000000011 /
b11100000000000000000011 8
b11100000000000000000011 :
b11 =
b0 E
b0 P
b110 7
b110 9
b110 <
1#
#380
0#
#390
0%
0*
b11110000 "
b11110000 2
b11110000 F
b11110000 L
b11110000 M
b100 =
b100000 H
b100000 K
b10000 G
b10000 J
b10000 E
b10000 P
b1 .
b1 ?
b1 N
b100000 D
b100000 Q
b10 -
b10 @
b10 O
b111 (
b111 6
b111 ;
b111 B
b11100000001001000000111 /
b11100000001001000000111 8
b11100000001001000000111 :
b11 7
b11 9
b11 <
b100 !
b100 )
b100 C
b100 S
1#
#400
0#
#410
b100000 "
b100000 2
b100000 F
b100000 L
b100000 M
00
b10 3
b10 5
b10 >
b10 I
1&
1,
b10000 H
b10000 K
b10 '
b10 4
b1 +
b1 A
b1 R
b10000 D
b10000 Q
b1 -
b1 @
b1 O
b0 (
b0 6
b0 ;
b0 B
b1000010001000100000000 /
b1000010001000100000000 8
b1000010001000100000000 :
b101 =
b100 7
b100 9
b100 <
1#
#420
0#
#430
11
b110 '
b110 4
b1111 +
b1111 A
b1111 R
b1111 .
b1111 ?
b1111 N
b0 -
b0 @
b0 O
b1 (
b1 6
b1 ;
b1 B
b101 "
b101 2
b101 F
b101 L
b101 M
b11011111111000000000001 /
b11011111111000000000001 8
b11011111111000000000001 :
b110 =
b1 H
b1 K
b100 G
b100 J
b101 7
b101 9
b101 <
b100 E
b100 P
b0 D
b0 Q
1#
#440
0#
#450
1%
1*
10
b11 3
b11 5
b11 >
b11 I
01
0&
0,
b0 H
b0 K
b0 "
b0 2
b0 F
b0 L
b0 M
b111 '
b111 4
b0 +
b0 A
b0 R
b0 .
b0 ?
b0 N
b11 (
b11 6
b11 ;
b11 B
b0 G
b0 J
b11100000000000000000011 /
b11100000000000000000011 8
b11100000000000000000011 :
b11 =
b0 E
b0 P
b110 7
b110 9
b110 <
1#
#460
0#
#470
b111 =
b100000 H
b100000 K
b100000 G
b100000 J
b100000 E
b100000 P
b1 .
b1 ?
b1 N
b100000 D
b100000 Q
b10 -
b10 @
b10 O
b111 (
b111 6
b111 ;
b111 B
b11100000001001000000111 /
b11100000001001000000111 8
b11100000001001000000111 :
b11 7
b11 9
b11 <
b101 !
b101 )
b101 C
b101 S
1#
#480
0#
#490
b0 H
b0 K
b0 G
b0 J
b0 E
b0 P
b0 .
b0 ?
b0 N
b0 D
b0 Q
b0 -
b0 @
b0 O
b11100000000000000000111 /
b11100000000000000000111 8
b11100000000000000000111 :
b111 7
b111 9
b111 <
1#
