instruction_memory.sv
module instruction_memory (input logic [7:0] PC, 
                           output logic [23:0] Instr); 

logic [24:0] data_ROM [0:255]; 

initial begin
    $readmemh("program.txt", data_ROM);
end

assign Instr = data_ROM[PC]; 

endmodule

pc.sv
module pc (input logic [7:0] immediate,
           input logic PCSrc, CLK, reset,
           output logic [7:0] PC);

    logic [7:0] PC_temp;
    
    always_comb begin

        if (PCSrc) begin
            PC_temp = immediate;
        end

        else begin
            PC_temp = PC + 8'b01;
        end            
        
    end


    always_ff @( posedge CLK ) begin

        if (reset) begin    
            PC <= 0;
        end 
        else begin
            PC <= PC_temp;
        end
            
    end

    
endmodule

instruction_memory_pc.sv
`include "instruction_memory.sv"
`include "pc.sv"

module instruction_memory_pc (input logic [7:0] immediate,
                              input logic PCSrc, CLK, reset, 
                              output logic [23:0] Instr);

    logic [7:0] PC;

    pc pc_in (immediate,PCSrc, CLK, reset,PC);

    instruction_memory instruction_memory_in (PC,Instr);

    
endmodule

instruction_memory_pc_tb.sv
`timescale 1ps/1ps
`include "instruction_memory_pc.sv"

module instruction_memory_pc_tb;

logic [7:0] immediate;
logic PCSrc, CLK, reset; 
logic [23:0] Instr;

instruction_memory_pc dut (immediate, PCSrc, CLK, reset, Instr);

initial begin
    CLK = 0;
    forever begin
        #10 CLK = ~CLK;
    end
end

initial begin
    $dumpfile("instruction_memory_pc_tb.vcd");
    $dumpvars(0,instruction_memory_pc_tb);

    reset = 0;immediate = 8'h00;
    PCSrc = 1;
    #10 
    #10 PCSrc = 0;
    #10
    #10
    #10 
    #10 
    #10 
    #10
    #10 
    #10 
    #10
    #10
    #10
    #10
    #10 PCSrc = 1;immediate = 8'h03;
    #10
    #10 PCSrc = 0;
    #10
    #10
    #10
    #10
    #10
    #10
    #10


    $finish;
end

initial begin
    $monitor("time = %3d, PCSrc = %d , immediate = %h, Instr = %h",$time, PCSrc, immediate, Instr);
end

endmodule

instruction_memory_pc_tb.vcd
$date
	Fri Mar 03 23:06:07 2023
$end
$version
	Icarus Verilog
$end
$timescale
	1ps
$end
$scope module instruction_memory_pc_tb $end
$var wire 24 ! Instr [23:0] $end
$var reg 1 " CLK $end
$var reg 1 # PCSrc $end
$var reg 8 $ immediate [7:0] $end
$var reg 1 % reset $end
$scope module dut $end
$var wire 1 " CLK $end
$var wire 1 # PCSrc $end
$var wire 8 & immediate [7:0] $end
$var wire 1 % reset $end
$var wire 8 ' PC [7:0] $end
$var wire 24 ( Instr [23:0] $end
$scope module instruction_memory_in $end
$var wire 8 ) PC [7:0] $end
$var wire 24 * Instr [23:0] $end
$upscope $end
$scope module pc_in $end
$var wire 1 " CLK $end
$var wire 1 # PCSrc $end
$var wire 8 + immediate [7:0] $end
$var wire 1 % reset $end
$var reg 8 , PC [7:0] $end
$var reg 8 - PC_temp [7:0] $end
$upscope $end
$upscope $end
$upscope $end
$enddefinitions $end
$comment Show the parameter values. $end
$dumpall
$end
#0
$dumpvars
b0 -
bx ,
b0 +
bx *
bx )
bx (
bx '
b0 &
0%
b0 $
1#
0"
bx !
$end
#10
b11000010000000000000001 !
b11000010000000000000001 (
b11000010000000000000001 *
b0 '
b0 )
b0 ,
1"
#20
b1 -
0#
0"
#30
b11000100000000000100000 !
b11000100000000000100000 (
b11000100000000000100000 *
b10 -
b1 '
b1 )
b1 ,
1"
#40
0"
#50
b11011110000000000000000 !
b11011110000000000000000 (
b11011110000000000000000 *
b11 -
b10 '
b10 )
b10 ,
1"
#60
0"
#70
b11100000001001000000111 !
b11100000001001000000111 (
b11100000001001000000111 *
b100 -
b11 '
b11 )
b11 ,
1"
#80
0"
#90
b1000010001000100000000 !
b1000010001000100000000 (
b1000010001000100000000 *
b101 -
b100 '
b100 )
b100 ,
1"
#100
0"
#110
b11011111111000000000001 !
b11011111111000000000001 (
b11011111111000000000001 *
b110 -
b101 '
b101 )
b101 ,
1"
#120
0"
#130
b11100000000000000000011 !
b11100000000000000000011 (
b11100000000000000000011 *
b111 -
b110 '
b110 )
b110 ,
1"
#140
0"
#150
b11100000000000000000111 !
b11100000000000000000111 (
b11100000000000000000111 *
b111 '
b111 )
b111 ,
b11 -
b11 $
b11 &
b11 +
1#
1"
#160
0"
#170
b11100000001001000000111 !
b11100000001001000000111 (
b11100000001001000000111 *
b11 '
b11 )
b11 ,
b100 -
0#
1"
#180
0"
#190
b1000010001000100000000 !
b1000010001000100000000 (
b1000010001000100000000 *
b101 -
b100 '
b100 )
b100 ,
1"
#200
0"
#210
b11011111111000000000001 !
b11011111111000000000001 (
b11011111111000000000001 *
b110 -
b101 '
b101 )
b101 ,
1"
#220
0"
#230
b11100000000000000000011 !
b11100000000000000000011 (
b11100000000000000000011 *
b111 -
b110 '
b110 )
b110 ,
1"
