pc.sv
module pc (input logic [7:0] immediate,
           input logic PCSrc, CLK, reset,
           output logic [7:0] PC);

    logic [7:0] PC_temp;
    
    always_comb begin

        if (PCSrc) begin
            PC_temp = immediate;
        end

        else begin
            PC_temp = PC + 8'b01;
        end            
        
    end


    always_ff @( posedge CLK ) begin

        if (reset) begin    
            PC <= 0;
        end 
        else begin
            PC <= PC_temp;
        end
            
    end

    
endmodule

pc_tb.sv
`timescale 1ps/1ps
`include "pc.sv"

module pc_tb;
logic [7:0] immediate;
logic PCSrc, CLK, reset;
logic [7:0] PC;

pc dut (immediate, PCSrc ,CLK ,reset ,PC);

initial begin
    CLK = 0;
    forever begin
        #10 CLK = ~CLK;
    end
end

initial begin
    $dumpfile("pc_tb.vcd");
    $dumpvars(0,pc_tb);

    reset = 0;immediate = 8'h00;
    PCSrc = 1;
    #10 
    #10 PCSrc = 0;
    #10 
    #10 
    #10 
    #10
    #10 
    #10 
    #10
    #10 PCSrc = 1;immediate = 8'h05;
    #10 PCSrc = 0;
    #10
    #10
    #10
    #10
    #10
    $finish;

end

initial begin
    $monitor("time = %3d, PCSrc = %b, immediate = %d, PC = %h", $time, PCSrc, immediate, PC);
end

endmodule

pc_tb.vcd
$date
	Fri Mar 03 23:03:31 2023
$end
$version
	Icarus Verilog
$end
$timescale
	1ps
$end
$scope module pc_tb $end
$var wire 8 ! PC [7:0] $end
$var reg 1 " CLK $end
$var reg 1 # PCSrc $end
$var reg 8 $ immediate [7:0] $end
$var reg 1 % reset $end
$scope module dut $end
$var wire 1 " CLK $end
$var wire 1 # PCSrc $end
$var wire 8 & immediate [7:0] $end
$var wire 1 % reset $end
$var reg 8 ' PC [7:0] $end
$var reg 8 ( PC_temp [7:0] $end
$upscope $end
$upscope $end
$enddefinitions $end
$comment Show the parameter values. $end
$dumpall
$end
#0
$dumpvars
b0 (
bx '
b0 &
0%
b0 $
1#
0"
bx !
$end
#10
b0 !
b0 '
1"
#20
b1 (
0#
0"
#30
b10 (
b1 !
b1 '
1"
#40
0"
#50
b11 (
b10 !
b10 '
1"
#60
0"
#70
b100 (
b11 !
b11 '
1"
#80
0"
#90
b101 (
b100 !
b100 '
1"
#100
b101 $
b101 &
1#
0"
#110
b110 (
b101 !
b101 '
0#
1"
#120
0"
#130
b111 (
b110 !
b110 '
1"
#140
0"
#150
b1000 (
b111 !
b111 '
1"
