reg_file.sv
module reg_file (input logic [3:0] RA1,RA2,WA,
                 input logic [7:0] ALUResult,
                 input logic write_enable,CLK,
                 output logic [7:0] RD1,RD2,cpu_out);
    
    logic [7:0] rf [0:15];
    assign RD1 = rf[RA1];
    assign RD2 = rf[RA2];

    always_comb begin
        rf[0] = 8'b0;
    end
    
    always_ff @( posedge CLK ) begin
        if (write_enable && WA > 0) begin
            rf[WA] <= ALUResult;
        end

        cpu_out <= rf[15];
    end

endmodule

alu.sv
module alu (input logic [7:0] SrcA,SrcB,
            input logic [1:0] ALUControl,
            output logic [7:0] ALUResult,
            output logic Zero);
    always_comb begin

        case(ALUControl)
        2'b00: ALUResult = SrcA & SrcB;
        2'b01: ALUResult = SrcA | SrcB;
        2'b10: ALUResult = SrcA + SrcB;
        2'b11: ALUResult = SrcA - SrcB;
        default: ALUResult = 8'bx;
        endcase

        if(ALUResult == 0) begin
            Zero = 1;
        end
        else begin
            Zero = 0;
        end
    end

  
endmodule

reg_file_alu.sv
`include "alu.sv"
`include "reg_file.sv"

module reg_file_alu (input logic [3:0] RA1,RA2,WA,
                     input logic [7:0] immediate,
                     input logic [1:0] ALUControl,
                     input logic write_enable, ALUSrc, CLK,
                     output logic [7:0] ALUResult,cpu_out,
                     output logic Zero);

    logic [7:0] SrcA,SrcB,RD1,RD2;

    alu alu_in (SrcA,SrcB,ALUControl,ALUResult,Zero);

    reg_file reg_file_in (RA1,RA2,WA,ALUResult,write_enable,CLK,RD1,RD2,cpu_out);

    always_comb begin

        SrcA = RD1;

        if (ALUSrc) begin
            SrcB = immediate;
        end
        else begin
            SrcB = RD2; 
        end
    end

endmodule

reg_file_alu_tb.sv
`timescale 1ps/1ps
`include "reg_file_alu.sv"

module reg_file_alu_tb;
logic [3:0] RA1,RA2,WA;
logic [7:0] immediate;
logic [1:0] ALUControl;
logic write_enable, ALUSrc, CLK;
logic [7:0] ALUResult,cpu_out;
logic Zero;

reg_file_alu dut (RA1,RA2,WA,immediate,ALUControl,write_enable, ALUSrc, CLK,ALUResult,cpu_out,Zero);

initial begin
    CLK = 0;
    forever begin
        #10 CLK = ~CLK;
    end
end

initial begin
    $dumpfile("reg_file_alu_tb.vcd");
    $dumpvars(0,reg_file_alu_tb);
    
    #10 WA = 0;write_enable = 1;immediate = 2;
    #10 ALUControl = 2'b10;

    for (int i = 0; i <= 15; i = i + 1) begin
        #10 ALUSrc = 1;
        #10 RA1 = i;RA2 = i;
        #10 WA = WA + 1;
    end

    RA1 = 7; RA2 = 8;
    #30;
    ALUControl = 2'b00;
    #30; 
    ALUControl = 2'b01;
    #30;
    ALUControl = 2'b10;
    #30;
    ALUControl = 2'b11;

    $finish;
end

initial begin
    $monitor("Time = %3d, ALUResult = %d, Zero = %b, cpu_out = %d",$time,ALUResult,Zero,cpu_out);
end


endmodule

reg_file_alu_tb.vcd
$date
	Mon Mar 06 12:33:27 2023
$end
$version
	Icarus Verilog
$end
$timescale
	1ps
$end
$scope module reg_file_alu_tb $end
$var wire 8 ! cpu_out [7:0] $end
$var wire 1 " Zero $end
$var wire 8 # ALUResult [7:0] $end
$var reg 2 $ ALUControl [1:0] $end
$var reg 1 % ALUSrc $end
$var reg 1 & CLK $end
$var reg 4 ' RA1 [3:0] $end
$var reg 4 ( RA2 [3:0] $end
$var reg 4 ) WA [3:0] $end
$var reg 8 * immediate [7:0] $end
$var reg 1 + write_enable $end
$scope module dut $end
$var wire 2 , ALUControl [1:0] $end
$var wire 1 % ALUSrc $end
$var wire 1 & CLK $end
$var wire 4 - RA1 [3:0] $end
$var wire 4 . RA2 [3:0] $end
$var wire 4 / WA [3:0] $end
$var wire 8 0 immediate [7:0] $end
$var wire 1 + write_enable $end
$var wire 8 1 cpu_out [7:0] $end
$var wire 1 " Zero $end
$var wire 8 2 RD2 [7:0] $end
$var wire 8 3 RD1 [7:0] $end
$var wire 8 4 ALUResult [7:0] $end
$var reg 8 5 SrcA [7:0] $end
$var reg 8 6 SrcB [7:0] $end
$scope module alu_in $end
$var wire 2 7 ALUControl [1:0] $end
$var wire 8 8 SrcA [7:0] $end
$var wire 8 9 SrcB [7:0] $end
$var reg 8 : ALUResult [7:0] $end
$var reg 1 " Zero $end
$upscope $end
$scope module reg_file_in $end
$var wire 8 ; ALUResult [7:0] $end
$var wire 1 & CLK $end
$var wire 4 < RA1 [3:0] $end
$var wire 4 = RA2 [3:0] $end
$var wire 8 > RD1 [7:0] $end
$var wire 8 ? RD2 [7:0] $end
$var wire 4 @ WA [3:0] $end
$var wire 1 + write_enable $end
$var reg 8 A cpu_out [7:0] $end
$upscope $end
$upscope $end
$scope begin $ivl_for_loop0 $end
$var integer 32 B i [31:0] $end
$upscope $end
$upscope $end
$enddefinitions $end
$comment Show the parameter values. $end
$dumpall
$end
#0
$dumpvars
b0 B
bx A
bx @
bx ?
bx >
bx =
bx <
bx ;
bx :
bx 9
bx 8
bx 7
bx 6
bx 5
bx 4
bx 3
bx 2
bx 1
bx 0
bx /
bx .
bx -
bx ,
x+
bx *
bx )
bx (
bx '
0&
x%
bx $
bx #
0"
bx !
$end
#10
b10 *
b10 0
1+
b0 )
b0 /
b0 @
1&
#20
b10 $
b10 ,
b10 7
0&
#30
b10 6
b10 9
1%
1&
#40
b10 #
b10 4
b10 :
b10 ;
b0 5
b0 8
b0 2
b0 ?
b0 (
b0 .
b0 =
b0 3
b0 >
b0 '
b0 -
b0 <
0&
#50
b1 B
b1 )
b1 /
b1 @
1&
#60
0&
#70
b100 #
b100 4
b100 :
b100 ;
b10 5
b10 8
b10 2
b10 ?
b1 (
b1 .
b1 =
b10 3
b10 >
b1 '
b1 -
b1 <
1&
#80
b10 B
b10 )
b10 /
b10 @
0&
#90
1&
#100
b110 #
b110 4
b110 :
b110 ;
b100 5
b100 8
b100 2
b100 ?
b10 (
b10 .
b10 =
b100 3
b100 >
b10 '
b10 -
b10 <
0&
#110
b11 B
b11 )
b11 /
b11 @
1&
#120
0&
#130
b1000 #
b1000 4
b1000 :
b1000 ;
b110 5
b110 8
b110 2
b110 ?
b11 (
b11 .
b11 =
b110 3
b110 >
b11 '
b11 -
b11 <
1&
#140
b100 B
b100 )
b100 /
b100 @
0&
#150
1&
#160
b1010 #
b1010 4
b1010 :
b1010 ;
b1000 5
b1000 8
b1000 2
b1000 ?
b100 (
b100 .
b100 =
b1000 3
b1000 >
b100 '
b100 -
b100 <
0&
#170
b101 B
b101 )
b101 /
b101 @
1&
#180
0&
#190
b1100 #
b1100 4
b1100 :
b1100 ;
b1010 5
b1010 8
b1010 2
b1010 ?
b101 (
b101 .
b101 =
b1010 3
b1010 >
b101 '
b101 -
b101 <
1&
#200
b110 B
b110 )
b110 /
b110 @
0&
#210
1&
#220
b1110 #
b1110 4
b1110 :
b1110 ;
b1100 5
b1100 8
b1100 2
b1100 ?
b110 (
b110 .
b110 =
b1100 3
b1100 >
b110 '
b110 -
b110 <
0&
#230
b111 B
b111 )
b111 /
b111 @
1&
#240
0&
#250
b10000 #
b10000 4
b10000 :
b10000 ;
b1110 5
b1110 8
b1110 2
b1110 ?
b111 (
b111 .
b111 =
b1110 3
b1110 >
b111 '
b111 -
b111 <
1&
#260
b1000 B
b1000 )
b1000 /
b1000 @
0&
#270
1&
#280
b10010 #
b10010 4
b10010 :
b10010 ;
b10000 5
b10000 8
b10000 2
b10000 ?
b1000 (
b1000 .
b1000 =
b10000 3
b10000 >
b1000 '
b1000 -
b1000 <
0&
#290
b1001 B
b1001 )
b1001 /
b1001 @
1&
#300
0&
#310
b10100 #
b10100 4
b10100 :
b10100 ;
b10010 5
b10010 8
b10010 2
b10010 ?
b1001 (
b1001 .
b1001 =
b10010 3
b10010 >
b1001 '
b1001 -
b1001 <
1&
#320
b1010 B
b1010 )
b1010 /
b1010 @
0&
#330
1&
#340
b10110 #
b10110 4
b10110 :
b10110 ;
b10100 5
b10100 8
b10100 2
b10100 ?
b1010 (
b1010 .
b1010 =
b10100 3
b10100 >
b1010 '
b1010 -
b1010 <
0&
#350
b1011 B
b1011 )
b1011 /
b1011 @
1&
#360
0&
#370
b11000 #
b11000 4
b11000 :
b11000 ;
b10110 5
b10110 8
b10110 2
b10110 ?
b1011 (
b1011 .
b1011 =
b10110 3
b10110 >
b1011 '
b1011 -
b1011 <
1&
#380
b1100 B
b1100 )
b1100 /
b1100 @
0&
#390
1&
#400
b11010 #
b11010 4
b11010 :
b11010 ;
b11000 5
b11000 8
b11000 2
b11000 ?
b1100 (
b1100 .
b1100 =
b11000 3
b11000 >
b1100 '
b1100 -
b1100 <
0&
#410
b1101 B
b1101 )
b1101 /
b1101 @
1&
#420
0&
#430
b11100 #
b11100 4
b11100 :
b11100 ;
b11010 5
b11010 8
b11010 2
b11010 ?
b1101 (
b1101 .
b1101 =
b11010 3
b11010 >
b1101 '
b1101 -
b1101 <
1&
#440
b1110 B
b1110 )
b1110 /
b1110 @
0&
#450
1&
#460
b11110 #
b11110 4
b11110 :
b11110 ;
b11100 5
b11100 8
b11100 2
b11100 ?
b1110 (
b1110 .
b1110 =
b11100 3
b11100 >
b1110 '
b1110 -
b1110 <
0&
#470
b1111 B
b1111 )
b1111 /
b1111 @
1&
#480
0&
#490
b11110 !
b11110 1
b11110 A
b100000 #
b100000 4
b100000 :
b100000 ;
b11110 5
b11110 8
b11110 2
b11110 ?
b1111 (
b1111 .
b1111 =
b11110 3
b11110 >
b1111 '
b1111 -
b1111 <
1&
#500
b10000 #
b10000 4
b10000 :
b10000 ;
b1110 5
b1110 8
b10000 2
b10000 ?
b1000 (
b1000 .
b1000 =
b1110 3
b1110 >
b111 '
b111 -
b111 <
b10000 B
b0 )
b0 /
b0 @
0&
#510
1&
#520
0&
#530
b10 #
b10 4
b10 :
b10 ;
1&
b0 $
b0 ,
b0 7
#540
0&
#550
1&
#560
b1110 #
b1110 4
b1110 :
b1110 ;
0&
b1 $
b1 ,
b1 7
#570
1&
#580
0&
#590
b10000 #
b10000 4
b10000 :
b10000 ;
1&
b10 $
b10 ,
b10 7
#600
0&
#610
1&
#620
b1100 #
b1100 4
b1100 :
b1100 ;
0&
b11 $
b11 ,
b11 7
