reg_file.sv
module reg_file (input logic [3:0] RA1,RA2,WA,
                 input logic [7:0] ALUResult,
                 input logic write_enable,CLK,
                 output logic [7:0] RD1,RD2,cpu_out);
    
    logic [7:0] rf [0:15];
    assign RD1 = rf[RA1];
    assign RD2 = rf[RA2];

    always_comb begin
        rf[0] = 8'b0;
    end
    
    always_ff @( posedge CLK ) begin
        if (write_enable && WA > 0) begin
            rf[WA] <= ALUResult;
        end

        cpu_out <= rf[15];
    end

endmodule

reg_file_tb.sv
`timescale 1ps/1ps
`include "reg_file.sv"

module reg_file_tb;
logic [3:0] RA1,RA2,WA;
logic [7:0] ALUResult,RD1,RD2,cpu_out;
logic write_enable,CLK;  

reg_file dut (RA1,RA2,WA,ALUResult,write_enable,CLK,RD1,RD2,cpu_out);

initial begin
    CLK = 0;
    forever begin
        #10 CLK = ~CLK;
    end
end

initial begin
    $dumpfile("reg_file_tb.vcd");
    $dumpvars(0,reg_file_tb);
    
    ALUResult = 5;WA = 0;write_enable = 1;
    for (int i = 0;i <= 15;i = i + 1 ) begin
        #10 WA = WA + 1;
        #10 ALUResult = ALUResult + 2;
        RA1 =WA-1;RA2 = WA;
    end
    
    RA1 = 1; RA2 = 2; WA = 0; ALUResult = 5; write_enable = 0; 
    #15 write_enable = 1;
    #20 WA = 1; ALUResult = 7;
    #20 WA = 5; ALUResult = 13;
    #20 WA = 15; ALUResult = 30;
    #20 write_enable = 0;
    #20 WA = 5; ALUResult = 11;
    #20 RA2 = 5;RA1 = 8;
    #30 write_enable = 1;
    #15 WA = 15; ALUResult = 23;
    #20 WA = 4; ALUResult=24;
    #20 RA1 = 4; RA2 = 15;

    $finish;
end

initial begin
    $monitor("time=%3d, write_enable = %b, RD1 = %d, RD2 = %d,cpu_out = %d",$time,write_enable,RD1,RD2,cpu_out);
end
    
endmodule

reg_file_tb.vcd
$date
	Fri Mar 03 22:53:47 2023
$end
$version
	Icarus Verilog
$end
$timescale
	1ps
$end
$scope module reg_file_tb $end
$var wire 8 ! cpu_out [7:0] $end
$var wire 8 " RD2 [7:0] $end
$var wire 8 # RD1 [7:0] $end
$var reg 8 $ ALUResult [7:0] $end
$var reg 1 % CLK $end
$var reg 4 & RA1 [3:0] $end
$var reg 4 ' RA2 [3:0] $end
$var reg 4 ( WA [3:0] $end
$var reg 1 ) write_enable $end
$scope module dut $end
$var wire 8 * ALUResult [7:0] $end
$var wire 1 % CLK $end
$var wire 4 + RA1 [3:0] $end
$var wire 4 , RA2 [3:0] $end
$var wire 8 - RD1 [7:0] $end
$var wire 8 . RD2 [7:0] $end
$var wire 4 / WA [3:0] $end
$var wire 1 ) write_enable $end
$var reg 8 0 cpu_out [7:0] $end
$upscope $end
$scope begin $ivl_for_loop0 $end
$var integer 32 1 i [31:0] $end
$upscope $end
$upscope $end
$enddefinitions $end
$comment Show the parameter values. $end
$dumpall
$end
#0
$dumpvars
b0 1
bx 0
b0 /
bx .
bx -
bx ,
bx +
b101 *
1)
b0 (
bx '
bx &
0%
b101 $
bx #
bx "
bx !
$end
#10
b1 (
b1 /
1%
#20
b1 1
b101 "
b101 .
b1 '
b1 ,
b0 #
b0 -
b0 &
b0 +
b111 $
b111 *
0%
#30
b10 (
b10 /
1%
#40
b10 1
b111 "
b111 .
b10 '
b10 ,
b101 #
b101 -
b1 &
b1 +
b1001 $
b1001 *
0%
#50
b11 (
b11 /
1%
#60
b11 1
b1001 "
b1001 .
b11 '
b11 ,
b111 #
b111 -
b10 &
b10 +
b1011 $
b1011 *
0%
#70
b100 (
b100 /
1%
#80
b100 1
b1011 "
b1011 .
b100 '
b100 ,
b1001 #
b1001 -
b11 &
b11 +
b1101 $
b1101 *
0%
#90
b101 (
b101 /
1%
#100
b101 1
b1101 "
b1101 .
b101 '
b101 ,
b1011 #
b1011 -
b100 &
b100 +
b1111 $
b1111 *
0%
#110
b110 (
b110 /
1%
#120
b110 1
b1111 "
b1111 .
b110 '
b110 ,
b1101 #
b1101 -
b101 &
b101 +
b10001 $
b10001 *
0%
#130
b111 (
b111 /
1%
#140
b111 1
b10001 "
b10001 .
b111 '
b111 ,
b1111 #
b1111 -
b110 &
b110 +
b10011 $
b10011 *
0%
#150
b1000 (
b1000 /
1%
#160
b1000 1
b10011 "
b10011 .
b1000 '
b1000 ,
b10001 #
b10001 -
b111 &
b111 +
b10101 $
b10101 *
0%
#170
b1001 (
b1001 /
1%
#180
b1001 1
b10101 "
b10101 .
b1001 '
b1001 ,
b10011 #
b10011 -
b1000 &
b1000 +
b10111 $
b10111 *
0%
#190
b1010 (
b1010 /
1%
#200
b1010 1
b10111 "
b10111 .
b1010 '
b1010 ,
b10101 #
b10101 -
b1001 &
b1001 +
b11001 $
b11001 *
0%
#210
b1011 (
b1011 /
1%
#220
b1011 1
b11001 "
b11001 .
b1011 '
b1011 ,
b10111 #
b10111 -
b1010 &
b1010 +
b11011 $
b11011 *
0%
#230
b1100 (
b1100 /
1%
#240
b1100 1
b11011 "
b11011 .
b1100 '
b1100 ,
b11001 #
b11001 -
b1011 &
b1011 +
b11101 $
b11101 *
0%
#250
b1101 (
b1101 /
1%
#260
b1101 1
b11101 "
b11101 .
b1101 '
b1101 ,
b11011 #
b11011 -
b1100 &
b1100 +
b11111 $
b11111 *
0%
#270
b1110 (
b1110 /
1%
#280
b1110 1
b11111 "
b11111 .
b1110 '
b1110 ,
b11101 #
b11101 -
b1101 &
b1101 +
b100001 $
b100001 *
0%
#290
b1111 (
b1111 /
1%
#300
b1111 1
b100001 "
b100001 .
b1111 '
b1111 ,
b11111 #
b11111 -
b1110 &
b1110 +
b100011 $
b100011 *
0%
#310
b100001 !
b100001 0
b0 (
b0 /
1%
#320
0)
b10000 1
b111 "
b111 .
b10 '
b10 ,
b101 #
b101 -
b1 &
b1 +
b101 $
b101 *
0%
#330
1%
#335
1)
#340
0%
#350
1%
#355
b111 $
b111 *
b1 (
b1 /
#360
0%
#370
b111 #
b111 -
1%
#375
b1101 $
b1101 *
b101 (
b101 /
#380
0%
#390
1%
#395
b11110 $
b11110 *
b1111 (
b1111 /
#400
0%
#410
1%
#415
0)
#420
0%
#430
b11110 !
b11110 0
1%
#435
b1011 $
b1011 *
b101 (
b101 /
#440
0%
#450
1%
#455
b10011 #
b10011 -
b1000 &
b1000 +
b1101 "
b1101 .
b101 '
b101 ,
#460
0%
#470
1%
#480
0%
#485
1)
#490
b1011 "
b1011 .
1%
#500
0%
b10111 $
b10111 *
b1111 (
b1111 /
#510
1%
#520
0%
b11000 $
b11000 *
b100 (
b100 /
#530
b10111 !
b10111 0
1%
#540
0%
b10111 "
b10111 .
b1111 '
b1111 ,
b11000 #
b11000 -
b100 &
b100 +
